src/__init__.py
src/api_client.py
src/auth.py
src/cli.py
src/config.py
src/jsonschema_validator.py
src/runner.py
src/schema_loader.py
ogc_sta_schema_validator-0.1.0.data/data/share/ogc-sta-schema-validator/config/config.example.yaml
ogc_sta_schema_validator-0.1.0.dist-info/METADATA
ogc_sta_schema_validator-0.1.0.dist-info/WHEEL
ogc_sta_schema_validator-0.1.0.dist-info/entry_points.txt
ogc_sta_schema_validator-0.1.0.dist-info/licenses/LICENSE
ogc_sta_schema_validator-0.1.0.dist-info/RECORD
