Metadata-Version: 2.4
Name: ogc-sta-schema-validator
Version: 0.1.0
Summary: Validation tool for OGC SensorThings API entities against configurable JSON schemas
Project-URL: Homepage, https://github.com/janbeckert/ogc-sta-schema-validator
Project-URL: Documentation, https://github.com/janbeckert/ogc-sta-schema-validator#readme
Project-URL: Repository, https://github.com/janbeckert/ogc-sta-schema-validator
Project-URL: Issues, https://github.com/janbeckert/ogc-sta-schema-validator/issues
Project-URL: Changelog, https://github.com/janbeckert/ogc-sta-schema-validator/blob/main/CHANGELOG.md
Author-email: Jan Beckert <jan@beckert-it.com>
License: MIT
License-File: LICENSE
Keywords: data-quality,frost-server,iot,json-schema,ogc,sensor,sensorthings,validation
Classifier: Development Status :: 4 - Beta
Classifier: Intended Audience :: Developers
Classifier: Intended Audience :: Science/Research
Classifier: License :: OSI Approved :: MIT License
Classifier: Operating System :: OS Independent
Classifier: Programming Language :: Python :: 3
Classifier: Programming Language :: Python :: 3.9
Classifier: Programming Language :: Python :: 3.10
Classifier: Programming Language :: Python :: 3.11
Classifier: Programming Language :: Python :: 3.12
Classifier: Topic :: Scientific/Engineering
Classifier: Topic :: Software Development :: Quality Assurance
Classifier: Topic :: Software Development :: Testing
Requires-Python: >=3.9
Requires-Dist: click>=8.1.7
Requires-Dist: dynaconf>=3.2.0
Requires-Dist: jsonschema>=4.19.0
Requires-Dist: python-dateutil>=2.8.2
Requires-Dist: python-dotenv>=1.0.0
Requires-Dist: pyyaml>=6.0.1
Requires-Dist: requests>=2.31.0
Requires-Dist: tabulate>=0.9.0
Provides-Extra: build
Requires-Dist: build>=1.0.0; extra == 'build'
Requires-Dist: twine>=4.0.0; extra == 'build'
Provides-Extra: dev
Requires-Dist: pytest-cov>=4.0.0; extra == 'dev'
Requires-Dist: pytest>=7.0.0; extra == 'dev'
Requires-Dist: ruff>=0.1.0; extra == 'dev'
